bloch_sphere_plotter/__init__.py
bloch_sphere_plotter/plot.py
bloch_sphere_plotter-0.1.0.dist-info/METADATA
bloch_sphere_plotter-0.1.0.dist-info/WHEEL
bloch_sphere_plotter-0.1.0.dist-info/top_level.txt
bloch_sphere_plotter-0.1.0.dist-info/RECORD
