Metadata-Version: 2.2
Name: bloch-sphere-plotter
Version: 0.1.0
Summary: A tool for plotting quantum states on the Bloch sphere
Author-email: Arun Moorthy <amoorth2@stanford.edu>
License: MIT
Requires-Python: >=3.8
Requires-Dist: numpy>=1.20.0
Requires-Dist: matplotlib>=3.5.0
Provides-Extra: dev
Requires-Dist: pytest>=7.0.0; extra == "dev"
Requires-Dist: pytest-cov>=4.0.0; extra == "dev"
